[
  {
    "id": 26140003,
    "latitude": "4527400",
    "longitude": "489700",
    "cp": "26140",
    "pop": "R",
    "adresse": "LES BUIS",
    "ville": "Anneyron",
    "services": "{\"service\": [\"Station de gonflage\", \"Vente de gaz domestique (Butane, Propane)\", \"DAB (Distributeur automatique de billets)\"]}",
    "prix": "[{\"@nom\": \"Gazole\", \"@id\": \"1\", \"@maj\": \"2025-01-20 06:49:31\", \"@valeur\": \"1.709\"}, {\"@nom\": \"E85\", \"@id\": \"3\", \"@maj\": \"2025-01-15 16:55:11\", \"@valeur\": \"0.758\"}, {\"@nom\": \"E10\", \"@id\": \"5\", \"@maj\": \"2025-01-16 06:50:42\", \"@valeur\": \"1.789\"}, {\"@nom\": \"SP98\", \"@id\": \"6\", \"@maj\": \"2025-01-20 06:49:32\", \"@valeur\": \"1.865\"}]",
    "rupture": "[{\"@nom\": \"SP95\", \"@id\": \"2\", \"@debut\": \"2024-03-29 14:31:51\", \"@fin\": \"\", \"@type\": \"definitive\"}, {\"@nom\": \"GPLc\", \"@id\": \"4\", \"@debut\": \"2019-04-12 09:20:32\", \"@fin\": \"\", \"@type\": \"definitive\"}]",
    "horaires": "{\"@automate-24-24\": \"\", \"jour\": [{\"@id\": \"1\", \"@nom\": \"Lundi\", \"@ferme\": \"\"}, {\"@id\": \"2\", \"@nom\": \"Mardi\", \"@ferme\": \"\"}, {\"@id\": \"3\", \"@nom\": \"Mercredi\", \"@ferme\": \"\"}, {\"@id\": \"4\", \"@nom\": \"Jeudi\", \"@ferme\": \"\"}, {\"@id\": \"5\", \"@nom\": \"Vendredi\", \"@ferme\": \"\"}, {\"@id\": \"6\", \"@nom\": \"Samedi\", \"@ferme\": \"\"}, {\"@id\": \"7\", \"@nom\": \"Dimanche\", \"@ferme\": \"\"}]}",
    "geom": {
      "lon": 4.897,
      "lat": 45.274
    },
    "gazole_maj": "2025-01-20T07:49:31+01:00",
    "gazole_prix": 1.709,
    "sp95_maj": null,
    "sp95_prix": null,
    "e85_maj": "2025-01-15T17:55:11+01:00",
    "e85_prix": 0.758,
    "gplc_maj": null,
    "gplc_prix": null,
    "e10_maj": "2025-01-16T07:50:42+01:00",
    "e10_prix": 1.789,
    "sp98_maj": "2025-01-20T07:49:32+01:00",
    "sp98_prix": 1.865,
    "e10_rupture_debut": null,
    "e10_rupture_type": null,
    "sp98_rupture_debut": null,
    "sp98_rupture_type": null,
    "sp95_rupture_debut": "2024-03-29T15:31:51+01:00",
    "sp95_rupture_type": "definitive",
    "e85_rupture_debut": null,
    "e85_rupture_type": null,
    "gplc_rupture_debut": "2019-04-12T11:20:32+02:00",
    "gplc_rupture_type": "definitive",
    "gazole_rupture_debut": null,
    "gazole_rupture_type": null,
    "carburants_disponibles": [
      "Gazole",
      "E85",
      "E10",
      "SP98"
    ],
    "carburants_indisponibles": [
      "SP95",
      "GPLc"
    ],
    "carburants_rupture_temporaire": null,
    "carburants_rupture_definitive": "SP95;GPLc",
    "horaires_automate_24_24": "Non",
    "services_service": [
      "Station de gonflage",
      "Vente de gaz domestique (Butane, Propane)",
      "DAB (Distributeur automatique de billets)"
    ],
    "departement": "Drôme",
    "code_departement": "26",
    "region": "Auvergne-Rhône-Alpes",
    "code_region": "84",
    "horaires_jour": null
  }
]