[
  {
    "id": 31190002,
    "latitude": "4334838.13042",
    "longitude": 147203.766924,
    "cp": "31190",
    "pop": "R",
    "adresse": "RN20",
    "ville": "Auterive",
    "horaires": null,
    "services": "{\"service\": [\"Vente de gaz domestique (Butane, Propane)\", \"DAB (Distributeur automatique de billets)\"]}",
    "prix": "[{\"@nom\": \"Gazole\", \"@id\": \"1\", \"@maj\": \"2023-11-18 07:41:17\", \"@valeur\": \"1.759\"}, {\"@nom\": \"SP95\", \"@id\": \"2\", \"@maj\": \"2023-11-10 05:46:04\", \"@valeur\": \"1.850\"}, {\"@nom\": \"E10\", \"@id\": \"5\", \"@maj\": \"2023-11-10 05:46:04\", \"@valeur\": \"1.780\"}, {\"@nom\": \"SP98\", \"@id\": \"6\", \"@maj\": \"2023-11-10 05:46:05\", \"@valeur\": \"1.855\"}]",
    "geom": {
      "lon": 1.47203766924,
      "lat": 43.348381304200004
    },
    "gazole_maj": "2023-11-18 07:41:17",
    "gazole_prix": "1.759",
    "sp95_maj": "2023-11-10 05:46:04",
    "sp95_prix": "1.850",
    "e85_maj": null,
    "e85_prix": null,
    "gplc_maj": null,
    "gplc_prix": null,
    "e10_maj": "2023-11-10 05:46:04",
    "e10_prix": "1.780",
    "sp98_maj": "2023-11-10 05:46:05",
    "sp98_prix": "1.855",
    "carburants_disponibles": [
      "Gazole",
      "SP95",
      "E10",
      "SP98"
    ],
    "carburants_indisponibles": [
      "E85",
      "GPLc"
    ],
    "horaires_automate_24_24": "Non",
    "services_service": [
      "Vente de gaz domestique (Butane, Propane)",
      "DAB (Distributeur automatique de billets)"
    ],
    "departement": "Haute-Garonne",
    "code_departement": "31",
    "region": "Occitanie",
    "code_region": "76"
  },
  {
    "id": 31190004,
    "latitude": "4335226",
    "longitude": 146970,
    "cp": "31190",
    "pop": "R",
    "adresse": "27 ROUTE DE TOULOUSE",
    "ville": "Auterive",
    "horaires": null,
    "services": null,
    "prix": "[{\"@nom\": \"Gazole\", \"@id\": \"1\", \"@maj\": \"2023-11-21 00:01:00\", \"@valeur\": \"1.762\"}, {\"@nom\": \"E85\", \"@id\": \"3\", \"@maj\": \"2023-11-21 00:01:00\", \"@valeur\": \"0.994\"}, {\"@nom\": \"E10\", \"@id\": \"5\", \"@maj\": \"2023-11-21 00:01:00\", \"@valeur\": \"1.784\"}, {\"@nom\": \"SP98\", \"@id\": \"6\", \"@maj\": \"2023-11-21 00:01:00\", \"@valeur\": \"1.859\"}]",
    "geom": {
      "lon": 1.4697,
      "lat": 43.35226
    },
    "gazole_maj": "2023-11-21 00:01:00",
    "gazole_prix": "1.762",
    "sp95_maj": null,
    "sp95_prix": null,
    "e85_maj": "2023-11-21 00:01:00",
    "e85_prix": "0.994",
    "gplc_maj": null,
    "gplc_prix": null,
    "e10_maj": "2023-11-21 00:01:00",
    "e10_prix": "1.784",
    "sp98_maj": "2023-11-21 00:01:00",
    "sp98_prix": "1.859",
    "carburants_disponibles": [
      "Gazole",
      "E85",
      "E10",
      "SP98"
    ],
    "carburants_indisponibles": [
      "SP95",
      "GPLc"
    ],
    "horaires_automate_24_24": "Non",
    "services_service": null,
    "departement": "Haute-Garonne",
    "code_departement": "31",
    "region": "Occitanie",
    "code_region": "76"
  },
  {
    "id": 31190003,
    "latitude": "4336353.8424",
    "longitude": 145777.136189,
    "cp": "31190",
    "pop": "R",
    "adresse": "89 Route de Toulouse",
    "ville": "Auterive",
    "horaires": null,
    "services": "{\"service\": [\"Vente de pétrole lampant\", \"Station de gonflage\", \"Location de véhicule\", \"Piste poids lourds\", \"Lavage automatique\", \"DAB (Distributeur automatique de billets)\"]}",
    "prix": "[{\"@nom\": \"Gazole\", \"@id\": \"1\", \"@maj\": \"2023-11-14 09:18:11\", \"@valeur\": \"1.775\"}, {\"@nom\": \"SP95\", \"@id\": \"2\", \"@maj\": \"2023-11-14 09:18:11\", \"@valeur\": \"1.850\"}, {\"@nom\": \"GPLc\", \"@id\": \"4\", \"@maj\": \"2023-10-30 14:49:55\", \"@valeur\": \"0.999\"}, {\"@nom\": \"E10\", \"@id\": \"5\", \"@maj\": \"2023-11-14 10:23:10\", \"@valeur\": \"1.780\"}, {\"@nom\": \"SP98\", \"@id\": \"6\", \"@maj\": \"2023-11-14 09:18:11\", \"@valeur\": \"1.855\"}]",
    "geom": {
      "lon": 1.4577713618900001,
      "lat": 43.363538424000005
    },
    "gazole_maj": "2023-11-14 09:18:11",
    "gazole_prix": "1.775",
    "sp95_maj": "2023-11-14 09:18:11",
    "sp95_prix": "1.850",
    "e85_maj": null,
    "e85_prix": null,
    "gplc_maj": "2023-10-30 14:49:55",
    "gplc_prix": "0.999",
    "e10_maj": "2023-11-14 10:23:10",
    "e10_prix": "1.780",
    "sp98_maj": "2023-11-14 09:18:11",
    "sp98_prix": "1.855",
    "carburants_disponibles": [
      "Gazole",
      "SP95",
      "GPLc",
      "E10",
      "SP98"
    ],
    "carburants_indisponibles": [
      "E85"
    ],
    "horaires_automate_24_24": "Non",
    "services_service": [
      "Vente de pétrole lampant",
      "Station de gonflage",
      "Location de véhicule",
      "Piste poids lourds",
      "Lavage automatique",
      "DAB (Distributeur automatique de billets)"
    ],
    "departement": "Haute-Garonne",
    "code_departement": "31",
    "region": "Occitanie",
    "code_region": "76"
  }
]