[
  {
    "id": 35260002,
    "latitude": "4867905.3250025",
    "longitude": -186562.98570839,
    "cp": "35260",
    "pop": "R",
    "adresse": "LA NOUVELLE VAGUE",
    "ville": "Cancale",
    "horaires": null,
    "services": null,
    "prix": "[{\"@nom\": \"Gazole\", \"@id\": \"1\", \"@maj\": \"2024-01-29 07:44:35\", \"@valeur\": \"1.719\"}, {\"@nom\": \"SP95\", \"@id\": \"2\", \"@maj\": \"2024-01-29 07:44:35\", \"@valeur\": \"1.775\"}, {\"@nom\": \"SP98\", \"@id\": \"6\", \"@maj\": \"2024-01-29 07:44:36\", \"@valeur\": \"1.819\"}]",
    "geom": {
      "lon": -1.8656298570839,
      "lat": 48.679053250025
    },
    "gazole_maj": "2024-01-29T08:44:35+01:00",
    "gazole_prix": "1.719",
    "sp95_maj": "2024-01-29T08:44:35+01:00",
    "sp95_prix": "1.775",
    "e85_maj": null,
    "e85_prix": null,
    "gplc_maj": null,
    "gplc_prix": null,
    "e10_maj": null,
    "e10_prix": null,
    "sp98_maj": "2024-01-29T08:44:36+01:00",
    "sp98_prix": "1.819",
    "carburants_disponibles": [
      "Gazole",
      "SP95",
      "SP98"
    ],
    "carburants_indisponibles": [
      "E85",
      "GPLc",
      "E10"
    ],
    "horaires_automate_24_24": "Non",
    "services_service": null,
    "departement": "Ille-et-Vilaine",
    "code_departement": "35",
    "region": "Bretagne",
    "code_region": "53"
  }
]