[
  {
    "id": 81800006,
    "latitude": "4379568.7",
    "longitude": 175609.5,
    "cp": "81800",
    "pop": "R",
    "adresse": "ZONE DES MASSIES",
    "ville": "Coufouleux",
    "horaires": "{\"@automate-24-24\": \"\", \"jour\": [{\"@id\": \"1\", \"@nom\": \"Lundi\", \"@ferme\": \"1\"}, {\"@id\": \"2\", \"@nom\": \"Mardi\", \"@ferme\": \"1\"}, {\"@id\": \"3\", \"@nom\": \"Mercredi\", \"@ferme\": \"1\"}, {\"@id\": \"4\", \"@nom\": \"Jeudi\", \"@ferme\": \"1\"}, {\"@id\": \"5\", \"@nom\": \"Vendredi\", \"@ferme\": \"1\"}, {\"@id\": \"6\", \"@nom\": \"Samedi\", \"@ferme\": \"1\"}, {\"@id\": \"7\", \"@nom\": \"Dimanche\", \"@ferme\": \"1\"}]}",
    "services": null,
    "prix": "[{\"@nom\": \"Gazole\", \"@id\": \"1\", \"@maj\": \"2023-12-14 07:47:30\", \"@valeur\": \"1.709\"}, {\"@nom\": \"E85\", \"@id\": \"3\", \"@maj\": \"2023-11-24 08:35:45\", \"@valeur\": \"0.959\"}, {\"@nom\": \"E10\", \"@id\": \"5\", \"@maj\": \"2023-12-14 07:47:31\", \"@valeur\": \"1.749\"}, {\"@nom\": \"SP98\", \"@id\": \"6\", \"@maj\": \"2023-12-14 07:47:31\", \"@valeur\": \"1.820\"}]",
    "geom": {
      "lon": 1.756095,
      "lat": 43.795687
    },
    "gazole_maj": "2023-12-14T08:47:30+01:00",
    "gazole_prix": "1.709",
    "sp95_maj": null,
    "sp95_prix": null,
    "e85_maj": "2023-11-24T09:35:45+01:00",
    "e85_prix": "0.959",
    "gplc_maj": null,
    "gplc_prix": null,
    "e10_maj": "2023-12-14T08:47:31+01:00",
    "e10_prix": "1.749",
    "sp98_maj": "2023-12-14T08:47:31+01:00",
    "sp98_prix": "1.820",
    "carburants_disponibles": [
      "Gazole",
      "E85",
      "E10",
      "SP98"
    ],
    "carburants_indisponibles": [
      "SP95",
      "GPLc"
    ],
    "horaires_automate_24_24": "Non",
    "services_service": null,
    "departement": "Tarn",
    "code_departement": "81",
    "region": "Occitanie",
    "code_region": "76"
  }
]