[
  {
    "id": 22430001,
    "latitude": "4862200",
    "longitude": -243900,
    "cp": "22430",
    "pop": "R",
    "adresse": "LES JEANNETTES",
    "ville": "Erquy",
    "horaires": "{\"@automate-24-24\": \"1\", \"jour\": [{\"@id\": \"1\", \"@nom\": \"Lundi\", \"@ferme\": \"\", \"horaire\": {\"@ouverture\": \"09.00\", \"@fermeture\": \"19.30\"}}, {\"@id\": \"2\", \"@nom\": \"Mardi\", \"@ferme\": \"\", \"horaire\": {\"@ouverture\": \"09.00\", \"@fermeture\": \"19.30\"}}, {\"@id\": \"3\", \"@nom\": \"Mercredi\", \"@ferme\": \"\", \"horaire\": {\"@ouverture\": \"09.00\", \"@fermeture\": \"19.30\"}}, {\"@id\": \"4\", \"@nom\": \"Jeudi\", \"@ferme\": \"\", \"horaire\": {\"@ouverture\": \"09.00\", \"@fermeture\": \"19.30\"}}, {\"@id\": \"5\", \"@nom\": \"Vendredi\", \"@ferme\": \"\", \"horaire\": {\"@ouverture\": \"09.00\", \"@fermeture\": \"19.30\"}}, {\"@id\": \"6\", \"@nom\": \"Samedi\", \"@ferme\": \"\", \"horaire\": {\"@ouverture\": \"09.00\", \"@fermeture\": \"19.30\"}}, {\"@id\": \"7\", \"@nom\": \"Dimanche\", \"@ferme\": \"1\"}]}",
    "services": "{\"service\": [\"Toilettes publiques\", \"Laverie\", \"Relais colis\", \"Boutique alimentaire\", \"Station de gonflage\", \"Location de véhicule\", \"Piste poids lourds\", \"Lavage automatique\", \"Lavage manuel\", \"Vente de gaz domestique (Butane, Propane)\", \"Vente d'additifs carburants\", \"Wifi\", \"Automate CB 24/24\", \"DAB (Distributeur automatique de billets)\"]}",
    "prix": "[{\"@nom\": \"Gazole\", \"@id\": \"1\", \"@maj\": \"2023-12-27 09:04:36\", \"@valeur\": \"1.709\"}, {\"@nom\": \"E85\", \"@id\": \"3\", \"@maj\": \"2023-12-26 09:47:01\", \"@valeur\": \"0.999\"}, {\"@nom\": \"E10\", \"@id\": \"5\", \"@maj\": \"2023-12-24 09:29:08\", \"@valeur\": \"1.719\"}, {\"@nom\": \"SP98\", \"@id\": \"6\", \"@maj\": \"2023-12-27 09:04:36\", \"@valeur\": \"1.809\"}]",
    "geom": {
      "lon": -2.439,
      "lat": 48.622
    },
    "gazole_maj": "2023-12-27T10:04:36+01:00",
    "gazole_prix": "1.709",
    "sp95_maj": null,
    "sp95_prix": null,
    "e85_maj": "2023-12-26T10:47:01+01:00",
    "e85_prix": "0.999",
    "gplc_maj": null,
    "gplc_prix": null,
    "e10_maj": "2023-12-24T10:29:08+01:00",
    "e10_prix": "1.719",
    "sp98_maj": "2023-12-27T10:04:36+01:00",
    "sp98_prix": "1.809",
    "carburants_disponibles": [
      "Gazole",
      "E85",
      "E10",
      "SP98"
    ],
    "carburants_indisponibles": [
      "SP95",
      "GPLc"
    ],
    "horaires_automate_24_24": "Oui",
    "services_service": [
      "Toilettes publiques",
      "Laverie",
      "Relais colis",
      "Boutique alimentaire",
      "Station de gonflage",
      "Location de véhicule",
      "Piste poids lourds",
      "Lavage automatique",
      "Lavage manuel",
      "Vente de gaz domestique (Butane, Propane)",
      "Vente d'additifs carburants",
      "Wifi",
      "Automate CB 24/24",
      "DAB (Distributeur automatique de billets)"
    ],
    "departement": "Côtes-d'Armor",
    "code_departement": "22",
    "region": "Bretagne",
    "code_region": "53"
  }
]