[
  {
    "id": 67140002,
    "latitude": "4841600",
    "longitude": "747600",
    "cp": "67140",
    "pop": "R",
    "adresse": "2 Route de Bourgheim",
    "ville": "Gertwiller",
    "horaires": "{\"@automate-24-24\": \"1\", \"jour\": [{\"@id\": \"1\", \"@nom\": \"Lundi\", \"@ferme\": \"\", \"horaire\": {\"@ouverture\": \"00.00\", \"@fermeture\": \"00.00\"}}, {\"@id\": \"2\", \"@nom\": \"Mardi\", \"@ferme\": \"\", \"horaire\": {\"@ouverture\": \"00.00\", \"@fermeture\": \"00.00\"}}, {\"@id\": \"3\", \"@nom\": \"Mercredi\", \"@ferme\": \"\", \"horaire\": {\"@ouverture\": \"00.00\", \"@fermeture\": \"00.00\"}}, {\"@id\": \"4\", \"@nom\": \"Jeudi\", \"@ferme\": \"\", \"horaire\": {\"@ouverture\": \"00.00\", \"@fermeture\": \"00.00\"}}, {\"@id\": \"5\", \"@nom\": \"Vendredi\", \"@ferme\": \"\", \"horaire\": {\"@ouverture\": \"00.00\", \"@fermeture\": \"00.00\"}}, {\"@id\": \"6\", \"@nom\": \"Samedi\", \"@ferme\": \"\", \"horaire\": {\"@ouverture\": \"00.00\", \"@fermeture\": \"00.00\"}}, {\"@id\": \"7\", \"@nom\": \"Dimanche\", \"@ferme\": \"\", \"horaire\": {\"@ouverture\": \"00.00\", \"@fermeture\": \"00.00\"}}]}",
    "services": "{\"service\": [\"Toilettes publiques\", \"Laverie\", \"Boutique alimentaire\", \"Boutique non alimentaire\", \"Restauration à emporter\", \"Restauration sur place\", \"Aire de camping-cars\", \"Location de véhicule\", \"Lavage automatique\", \"Lavage manuel\", \"Vente de gaz domestique (Butane, Propane)\", \"Wifi\", \"Automate CB 24/24\", \"DAB (Distributeur automatique de billets)\"]}",
    "prix": "[{\"@nom\": \"Gazole\", \"@id\": \"1\", \"@maj\": \"2024-04-20 08:57:25\", \"@valeur\": \"1.738\"}, {\"@nom\": \"E10\", \"@id\": \"5\", \"@maj\": \"2024-04-16 08:12:33\", \"@valeur\": \"1.859\"}, {\"@nom\": \"SP98\", \"@id\": \"6\", \"@maj\": \"2024-04-16 08:12:33\", \"@valeur\": \"1.934\"}]",
    "rupture": "[{\"@nom\": \"E85\", \"@id\": \"3\", \"@debut\": \"2017-09-04 10:52:44\", \"@fin\": \"\", \"@type\": \"definitive\"}, {\"@nom\": \"GPLc\", \"@id\": \"4\", \"@debut\": \"2017-09-04 10:52:44\", \"@fin\": \"\", \"@type\": \"definitive\"}, {\"@nom\": \"SP95\", \"@id\": \"2\", \"@debut\": \"2022-01-24 12:10:29\", \"@fin\": \"\", \"@type\": \"definitive\"}]",
    "geom": {
      "lon": 7.476,
      "lat": 48.416
    },
    "gazole_maj": "2024-04-20T10:57:25+02:00",
    "gazole_prix": 1.738,
    "sp95_maj": null,
    "sp95_prix": null,
    "e85_maj": null,
    "e85_prix": null,
    "gplc_maj": null,
    "gplc_prix": null,
    "e10_maj": "2024-04-16T10:12:33+02:00",
    "e10_prix": 1.859,
    "sp98_maj": "2024-04-16T10:12:33+02:00",
    "sp98_prix": 1.934,
    "e10_rupture_debut": null,
    "e10_rupture_type": null,
    "sp98_rupture_debut": null,
    "sp98_rupture_type": null,
    "sp95_rupture_debut": "2022-01-24T13:10:29+01:00",
    "sp95_rupture_type": "definitive",
    "e85_rupture_debut": "2017-09-04T12:52:44+02:00",
    "e85_rupture_type": "definitive",
    "gplc_rupture_debut": "2017-09-04T12:52:44+02:00",
    "gplc_rupture_type": "definitive",
    "gazole_rupture_debut": null,
    "gazole_rupture_type": null,
    "carburants_disponibles": [
      "Gazole",
      "E10",
      "SP98"
    ],
    "carburants_indisponibles": [
      "SP95",
      "E85",
      "GPLc"
    ],
    "carburants_rupture_temporaire": null,
    "carburants_rupture_definitive": "SP95;E85;GPLc",
    "horaires_automate_24_24": "Oui",
    "services_service": [
      "Toilettes publiques",
      "Laverie",
      "Boutique alimentaire",
      "Boutique non alimentaire",
      "Restauration à emporter",
      "Restauration sur place",
      "Aire de camping-cars",
      "Location de véhicule",
      "Lavage automatique",
      "Lavage manuel",
      "Vente de gaz domestique (Butane, Propane)",
      "Wifi",
      "Automate CB 24/24",
      "DAB (Distributeur automatique de billets)"
    ],
    "departement": "Bas-Rhin",
    "code_departement": "67",
    "region": "Grand Est",
    "code_region": "44",
    "horaires_jour": "Automate-24-24, Lundi00.00-00.00, Mardi00.00-00.00, Mercredi00.00-00.00, Jeudi00.00-00.00, Vendredi00.00-00.00, Samedi00.00-00.00, Dimanche00.00-00.00"
  }
]