[
  {
    "id": 70700004,
    "latitude": "4741100",
    "longitude": 581900,
    "cp": "70700",
    "pop": "R",
    "adresse": "Rue Sous les Vorpes",
    "ville": "Gy",
    "horaires": "{\"@automate-24-24\": \"\", \"jour\": [{\"@id\": \"1\", \"@nom\": \"Lundi\", \"@ferme\": \"\"}, {\"@id\": \"2\", \"@nom\": \"Mardi\", \"@ferme\": \"\"}, {\"@id\": \"3\", \"@nom\": \"Mercredi\", \"@ferme\": \"\"}, {\"@id\": \"4\", \"@nom\": \"Jeudi\", \"@ferme\": \"\"}, {\"@id\": \"5\", \"@nom\": \"Vendredi\", \"@ferme\": \"\"}, {\"@id\": \"6\", \"@nom\": \"Samedi\", \"@ferme\": \"\"}, {\"@id\": \"7\", \"@nom\": \"Dimanche\", \"@ferme\": \"\"}]}",
    "services": "{\"service\": [\"Lavage manuel\", \"Vente de gaz domestique (Butane, Propane)\"]}",
    "prix": "[{\"@nom\": \"Gazole\", \"@id\": \"1\", \"@maj\": \"2023-12-22 08:24:28\", \"@valeur\": \"1.682\"}, {\"@nom\": \"E10\", \"@id\": \"5\", \"@maj\": \"2023-12-22 08:24:28\", \"@valeur\": \"1.717\"}, {\"@nom\": \"SP98\", \"@id\": \"6\", \"@maj\": \"2023-12-22 08:24:28\", \"@valeur\": \"1.790\"}]",
    "geom": {
      "lon": 5.819,
      "lat": 47.411
    },
    "gazole_maj": "2023-12-22T09:24:28+01:00",
    "gazole_prix": "1.682",
    "sp95_maj": null,
    "sp95_prix": null,
    "e85_maj": null,
    "e85_prix": null,
    "gplc_maj": null,
    "gplc_prix": null,
    "e10_maj": "2023-12-22T09:24:28+01:00",
    "e10_prix": "1.717",
    "sp98_maj": "2023-12-22T09:24:28+01:00",
    "sp98_prix": "1.790",
    "carburants_disponibles": [
      "Gazole",
      "E10",
      "SP98"
    ],
    "carburants_indisponibles": [
      "SP95",
      "E85",
      "GPLc"
    ],
    "horaires_automate_24_24": "Non",
    "services_service": [
      "Lavage manuel",
      "Vente de gaz domestique (Butane, Propane)"
    ],
    "departement": "Haute-Saône",
    "code_departement": "70",
    "region": "Bourgogne-Franche-Comté",
    "code_region": "27"
  }
]