[
  {
    "id": 13118001,
    "latitude": "4359886.3932079",
    "longitude": "493570.38705557",
    "cp": "13118",
    "pop": "R",
    "adresse": "74 AVENUE DE LA CRAU",
    "ville": "Istres",
    "services": "{\"service\": [\"Lavage automatique\", \"Automate CB 24/24\"]}",
    "prix": "[{\"@nom\": \"Gazole\", \"@id\": \"1\", \"@maj\": \"2025-04-07 13:08:05\", \"@valeur\": \"1.569\"}, {\"@nom\": \"E85\", \"@id\": \"3\", \"@maj\": \"2025-04-07 13:08:05\", \"@valeur\": \"0.799\"}, {\"@nom\": \"E10\", \"@id\": \"5\", \"@maj\": \"2025-04-07 13:08:05\", \"@valeur\": \"1.669\"}, {\"@nom\": \"SP98\", \"@id\": \"6\", \"@maj\": \"2025-04-07 13:08:05\", \"@valeur\": \"1.759\"}]",
    "rupture": "[{\"@nom\": \"GPLc\", \"@id\": \"4\", \"@debut\": \"2024-02-20 15:25:33\", \"@fin\": \"\", \"@type\": \"definitive\"}, {\"@nom\": \"SP95\", \"@id\": \"2\", \"@debut\": \"2023-11-29 12:27:43\", \"@fin\": \"\", \"@type\": \"temporaire\"}]",
    "horaires": "{\"@automate-24-24\": \"1\", \"jour\": [{\"@id\": \"1\", \"@nom\": \"Lundi\", \"@ferme\": \"1\", \"horaire\": {\"@ouverture\": \"01.00\", \"@fermeture\": \"01.00\"}}, {\"@id\": \"2\", \"@nom\": \"Mardi\", \"@ferme\": \"1\", \"horaire\": {\"@ouverture\": \"01.00\", \"@fermeture\": \"01.00\"}}, {\"@id\": \"3\", \"@nom\": \"Mercredi\", \"@ferme\": \"1\", \"horaire\": {\"@ouverture\": \"01.00\", \"@fermeture\": \"01.00\"}}, {\"@id\": \"4\", \"@nom\": \"Jeudi\", \"@ferme\": \"1\", \"horaire\": {\"@ouverture\": \"01.00\", \"@fermeture\": \"01.00\"}}, {\"@id\": \"5\", \"@nom\": \"Vendredi\", \"@ferme\": \"1\", \"horaire\": {\"@ouverture\": \"01.00\", \"@fermeture\": \"01.00\"}}, {\"@id\": \"6\", \"@nom\": \"Samedi\", \"@ferme\": \"1\", \"horaire\": {\"@ouverture\": \"01.00\", \"@fermeture\": \"01.00\"}}, {\"@id\": \"7\", \"@nom\": \"Dimanche\", \"@ferme\": \"1\", \"horaire\": {\"@ouverture\": \"01.00\", \"@fermeture\": \"01.00\"}}]}",
    "geom": {
      "lon": 4.935703870555701,
      "lat": 43.598863932079006
    },
    "gazole_maj": "2025-04-07T15:08:05+02:00",
    "gazole_prix": 1.569,
    "sp95_maj": null,
    "sp95_prix": null,
    "e85_maj": "2025-04-07T15:08:05+02:00",
    "e85_prix": 0.799,
    "gplc_maj": null,
    "gplc_prix": null,
    "e10_maj": "2025-04-07T15:08:05+02:00",
    "e10_prix": 1.669,
    "sp98_maj": "2025-04-07T15:08:05+02:00",
    "sp98_prix": 1.759,
    "e10_rupture_debut": null,
    "e10_rupture_type": null,
    "sp98_rupture_debut": null,
    "sp98_rupture_type": null,
    "sp95_rupture_debut": "2023-11-29T13:27:43+01:00",
    "sp95_rupture_type": "temporaire",
    "e85_rupture_debut": null,
    "e85_rupture_type": null,
    "gplc_rupture_debut": "2024-02-20T16:25:33+01:00",
    "gplc_rupture_type": "definitive",
    "gazole_rupture_debut": null,
    "gazole_rupture_type": null,
    "carburants_disponibles": [
      "Gazole",
      "E85",
      "E10",
      "SP98"
    ],
    "carburants_indisponibles": [
      "SP95",
      "GPLc"
    ],
    "carburants_rupture_temporaire": "SP95",
    "carburants_rupture_definitive": "GPLc",
    "horaires_automate_24_24": "Oui",
    "services_service": [
      "Lavage automatique",
      "Automate CB 24/24"
    ],
    "departement": "Bouches-du-Rhône",
    "code_departement": "13",
    "region": "Provence-Alpes-Côte d'Azur",
    "code_region": "93",
    "horaires_jour": "Automate-24-24, Lundi01.00-01.00, Mardi01.00-01.00, Mercredi01.00-01.00, Jeudi01.00-01.00, Vendredi01.00-01.00, Samedi01.00-01.00, Dimanche01.00-01.00"
  },
  {
    "id": 13800010,
    "latitude": "4350100",
    "longitude": "498700",
    "cp": "13800",
    "pop": "R",
    "adresse": "22 Avenue Félix GOUIN",
    "ville": "Istres",
    "services": "{\"service\": [\"Toilettes publiques\", \"Boutique alimentaire\", \"Boutique non alimentaire\", \"Restauration à emporter\", \"Vente de pétrole lampant\", \"Station de gonflage\", \"Carburant additivé\", \"Lavage automatique\", \"Vente de gaz domestique (Butane, Propane)\", \"Vente d'additifs carburants\", \"Wifi\", \"Automate CB 24/24\"]}",
    "prix": "[{\"@nom\": \"Gazole\", \"@id\": \"1\", \"@maj\": \"2025-04-07 08:17:19\", \"@valeur\": \"1.662\"}, {\"@nom\": \"SP95\", \"@id\": \"2\", \"@maj\": \"2025-04-07 08:17:19\", \"@valeur\": \"1.836\"}, {\"@nom\": \"SP98\", \"@id\": \"6\", \"@maj\": \"2025-04-07 08:17:20\", \"@valeur\": \"1.916\"}]",
    "rupture": "[{\"@nom\": \"E85\", \"@id\": \"3\", \"@debut\": \"2020-01-04 10:36:08\", \"@fin\": \"\", \"@type\": \"definitive\"}, {\"@nom\": \"GPLc\", \"@id\": \"4\", \"@debut\": \"2020-01-04 10:36:08\", \"@fin\": \"\", \"@type\": \"definitive\"}, {\"@nom\": \"E10\", \"@id\": \"5\", \"@debut\": \"2020-01-04 10:36:08\", \"@fin\": \"\", \"@type\": \"definitive\"}]",
    "horaires": "{\"@automate-24-24\": \"1\", \"jour\": [{\"@id\": \"1\", \"@nom\": \"Lundi\", \"@ferme\": \"\", \"horaire\": {\"@ouverture\": \"07.00\", \"@fermeture\": \"19.00\"}}, {\"@id\": \"2\", \"@nom\": \"Mardi\", \"@ferme\": \"\", \"horaire\": {\"@ouverture\": \"07.00\", \"@fermeture\": \"19.00\"}}, {\"@id\": \"3\", \"@nom\": \"Mercredi\", \"@ferme\": \"\", \"horaire\": {\"@ouverture\": \"07.00\", \"@fermeture\": \"19.00\"}}, {\"@id\": \"4\", \"@nom\": \"Jeudi\", \"@ferme\": \"\", \"horaire\": {\"@ouverture\": \"07.00\", \"@fermeture\": \"19.00\"}}, {\"@id\": \"5\", \"@nom\": \"Vendredi\", \"@ferme\": \"\", \"horaire\": {\"@ouverture\": \"07.00\", \"@fermeture\": \"19.00\"}}, {\"@id\": \"6\", \"@nom\": \"Samedi\", \"@ferme\": \"\", \"horaire\": {\"@ouverture\": \"07.00\", \"@fermeture\": \"19.00\"}}, {\"@id\": \"7\", \"@nom\": \"Dimanche\", \"@ferme\": \"1\"}]}",
    "geom": {
      "lon": 4.987,
      "lat": 43.501
    },
    "gazole_maj": "2025-04-07T10:17:19+02:00",
    "gazole_prix": 1.662,
    "sp95_maj": "2025-04-07T10:17:19+02:00",
    "sp95_prix": 1.836,
    "e85_maj": null,
    "e85_prix": null,
    "gplc_maj": null,
    "gplc_prix": null,
    "e10_maj": null,
    "e10_prix": null,
    "sp98_maj": "2025-04-07T10:17:20+02:00",
    "sp98_prix": 1.916,
    "e10_rupture_debut": "2020-01-04T11:36:08+01:00",
    "e10_rupture_type": "definitive",
    "sp98_rupture_debut": null,
    "sp98_rupture_type": null,
    "sp95_rupture_debut": null,
    "sp95_rupture_type": null,
    "e85_rupture_debut": "2020-01-04T11:36:08+01:00",
    "e85_rupture_type": "definitive",
    "gplc_rupture_debut": "2020-01-04T11:36:08+01:00",
    "gplc_rupture_type": "definitive",
    "gazole_rupture_debut": null,
    "gazole_rupture_type": null,
    "carburants_disponibles": [
      "Gazole",
      "SP95",
      "SP98"
    ],
    "carburants_indisponibles": [
      "E85",
      "GPLc",
      "E10"
    ],
    "carburants_rupture_temporaire": null,
    "carburants_rupture_definitive": "E85;GPLc;E10",
    "horaires_automate_24_24": "Oui",
    "services_service": [
      "Toilettes publiques",
      "Boutique alimentaire",
      "Boutique non alimentaire",
      "Restauration à emporter",
      "Vente de pétrole lampant",
      "Station de gonflage",
      "Carburant additivé",
      "Lavage automatique",
      "Vente de gaz domestique (Butane, Propane)",
      "Vente d'additifs carburants",
      "Wifi",
      "Automate CB 24/24"
    ],
    "departement": "Bouches-du-Rhône",
    "code_departement": "13",
    "region": "Provence-Alpes-Côte d'Azur",
    "code_region": "93",
    "horaires_jour": "Automate-24-24, Lundi07.00-19.00, Mardi07.00-19.00, Mercredi07.00-19.00, Jeudi07.00-19.00, Vendredi07.00-19.00, Samedi07.00-19.00, Dimanche"
  },
  {
    "id": 13800004,
    "latitude": "4352300",
    "longitude": "496400",
    "cp": "13800",
    "pop": "R",
    "adresse": "Quartier les Craux",
    "ville": "Istres",
    "services": "{\"service\": [\"Boutique alimentaire\", \"Boutique non alimentaire\", \"Vente de gaz domestique (Butane, Propane)\"]}",
    "prix": "[{\"@nom\": \"Gazole\", \"@id\": \"1\", \"@maj\": \"2025-04-05 08:00:10\", \"@valeur\": \"1.545\"}, {\"@nom\": \"SP95\", \"@id\": \"2\", \"@maj\": \"2025-03-20 07:45:00\", \"@valeur\": \"1.709\"}, {\"@nom\": \"GPLc\", \"@id\": \"4\", \"@maj\": \"2025-02-24 07:55:35\", \"@valeur\": \"0.908\"}, {\"@nom\": \"E10\", \"@id\": \"5\", \"@maj\": \"2025-04-04 08:00:00\", \"@valeur\": \"1.649\"}, {\"@nom\": \"SP98\", \"@id\": \"6\", \"@maj\": \"2025-03-12 07:51:31\", \"@valeur\": \"1.739\"}]",
    "rupture": "{\"@nom\": \"E85\", \"@id\": \"3\", \"@debut\": \"2023-04-03 11:34:42\", \"@fin\": \"\", \"@type\": \"temporaire\"}",
    "horaires": null,
    "geom": {
      "lon": 4.964,
      "lat": 43.523
    },
    "gazole_maj": "2025-04-05T10:00:10+02:00",
    "gazole_prix": 1.545,
    "sp95_maj": "2025-03-20T08:45:00+01:00",
    "sp95_prix": 1.709,
    "e85_maj": null,
    "e85_prix": null,
    "gplc_maj": "2025-02-24T08:55:35+01:00",
    "gplc_prix": 0.908,
    "e10_maj": "2025-04-04T10:00:00+02:00",
    "e10_prix": 1.649,
    "sp98_maj": "2025-03-12T08:51:31+01:00",
    "sp98_prix": 1.739,
    "e10_rupture_debut": null,
    "e10_rupture_type": null,
    "sp98_rupture_debut": null,
    "sp98_rupture_type": null,
    "sp95_rupture_debut": null,
    "sp95_rupture_type": null,
    "e85_rupture_debut": "2023-04-03T13:34:42+02:00",
    "e85_rupture_type": "temporaire",
    "gplc_rupture_debut": null,
    "gplc_rupture_type": null,
    "gazole_rupture_debut": null,
    "gazole_rupture_type": null,
    "carburants_disponibles": [
      "Gazole",
      "SP95",
      "GPLc",
      "E10",
      "SP98"
    ],
    "carburants_indisponibles": [
      "E85"
    ],
    "carburants_rupture_temporaire": "E85",
    "carburants_rupture_definitive": null,
    "horaires_automate_24_24": "Non",
    "services_service": [
      "Boutique alimentaire",
      "Boutique non alimentaire",
      "Vente de gaz domestique (Butane, Propane)"
    ],
    "departement": "Bouches-du-Rhône",
    "code_departement": "13",
    "region": "Provence-Alpes-Côte d'Azur",
    "code_region": "93",
    "horaires_jour": null
  },
  {
    "id": 13800011,
    "latitude": "4349800",
    "longitude": "497900",
    "cp": "13800",
    "pop": "R",
    "adresse": "ROUTE DE FOS SUR MER",
    "ville": "Istres",
    "services": "{\"service\": [\"Carburant additivé\", \"Vente de gaz domestique (Butane, Propane)\", \"DAB (Distributeur automatique de billets)\"]}",
    "prix": "[{\"@nom\": \"Gazole\", \"@id\": \"1\", \"@maj\": \"2025-04-07 08:00:00\", \"@valeur\": \"1.548\"}, {\"@nom\": \"GPLc\", \"@id\": \"4\", \"@maj\": \"2025-03-24 06:00:37\", \"@valeur\": \"0.939\"}, {\"@nom\": \"E10\", \"@id\": \"5\", \"@maj\": \"2025-04-07 08:00:00\", \"@valeur\": \"1.641\"}, {\"@nom\": \"SP98\", \"@id\": \"6\", \"@maj\": \"2025-04-07 08:00:00\", \"@valeur\": \"1.738\"}]",
    "rupture": "[{\"@nom\": \"E85\", \"@id\": \"3\", \"@debut\": \"2024-05-16 06:58:52\", \"@fin\": \"\", \"@type\": \"definitive\"}, {\"@nom\": \"SP95\", \"@id\": \"2\", \"@debut\": \"2024-05-14 08:56:50\", \"@fin\": \"\", \"@type\": \"definitive\"}]",
    "horaires": "{\"@automate-24-24\": \"\", \"jour\": [{\"@id\": \"1\", \"@nom\": \"Lundi\", \"@ferme\": \"1\"}, {\"@id\": \"2\", \"@nom\": \"Mardi\", \"@ferme\": \"1\"}, {\"@id\": \"3\", \"@nom\": \"Mercredi\", \"@ferme\": \"1\"}, {\"@id\": \"4\", \"@nom\": \"Jeudi\", \"@ferme\": \"1\"}, {\"@id\": \"5\", \"@nom\": \"Vendredi\", \"@ferme\": \"1\"}, {\"@id\": \"6\", \"@nom\": \"Samedi\", \"@ferme\": \"1\"}, {\"@id\": \"7\", \"@nom\": \"Dimanche\", \"@ferme\": \"1\"}]}",
    "geom": {
      "lon": 4.979,
      "lat": 43.498
    },
    "gazole_maj": "2025-04-07T10:00:00+02:00",
    "gazole_prix": 1.548,
    "sp95_maj": null,
    "sp95_prix": null,
    "e85_maj": null,
    "e85_prix": null,
    "gplc_maj": "2025-03-24T07:00:37+01:00",
    "gplc_prix": 0.939,
    "e10_maj": "2025-04-07T10:00:00+02:00",
    "e10_prix": 1.641,
    "sp98_maj": "2025-04-07T10:00:00+02:00",
    "sp98_prix": 1.738,
    "e10_rupture_debut": null,
    "e10_rupture_type": null,
    "sp98_rupture_debut": null,
    "sp98_rupture_type": null,
    "sp95_rupture_debut": "2024-05-14T10:56:50+02:00",
    "sp95_rupture_type": "definitive",
    "e85_rupture_debut": "2024-05-16T08:58:52+02:00",
    "e85_rupture_type": "definitive",
    "gplc_rupture_debut": null,
    "gplc_rupture_type": null,
    "gazole_rupture_debut": null,
    "gazole_rupture_type": null,
    "carburants_disponibles": [
      "Gazole",
      "GPLc",
      "E10",
      "SP98"
    ],
    "carburants_indisponibles": [
      "SP95",
      "E85"
    ],
    "carburants_rupture_temporaire": null,
    "carburants_rupture_definitive": "SP95;E85",
    "horaires_automate_24_24": "Non",
    "services_service": [
      "Carburant additivé",
      "Vente de gaz domestique (Butane, Propane)",
      "DAB (Distributeur automatique de billets)"
    ],
    "departement": "Bouches-du-Rhône",
    "code_departement": "13",
    "region": "Provence-Alpes-Côte d'Azur",
    "code_region": "93",
    "horaires_jour": null
  },
  {
    "id": 13800009,
    "latitude": "4349500",
    "longitude": "498600",
    "cp": "13800",
    "pop": "R",
    "adresse": "Avenue Félix Gouin",
    "ville": "Istres",
    "services": "{\"service\": [\"Toilettes publiques\", \"Boutique alimentaire\", \"Boutique non alimentaire\", \"Restauration à emporter\", \"Station de gonflage\", \"Carburant additivé\", \"Location de véhicule\", \"Lavage automatique\", \"Lavage manuel\", \"Vente de gaz domestique (Butane, Propane)\", \"Vente d'additifs carburants\", \"Wifi\"]}",
    "prix": "[{\"@nom\": \"Gazole\", \"@id\": \"1\", \"@maj\": \"2025-04-02 11:14:14\", \"@valeur\": \"1.619\"}, {\"@nom\": \"SP95\", \"@id\": \"2\", \"@maj\": \"2025-04-02 11:14:14\", \"@valeur\": \"1.723\"}, {\"@nom\": \"E10\", \"@id\": \"5\", \"@maj\": \"2025-04-02 11:14:15\", \"@valeur\": \"1.699\"}, {\"@nom\": \"SP98\", \"@id\": \"6\", \"@maj\": \"2025-04-02 11:14:15\", \"@valeur\": \"1.799\"}]",
    "rupture": "[{\"@nom\": \"E85\", \"@id\": \"3\", \"@debut\": \"2017-09-06 20:27:15\", \"@fin\": \"\", \"@type\": \"definitive\"}, {\"@nom\": \"GPLc\", \"@id\": \"4\", \"@debut\": \"2017-09-06 20:27:15\", \"@fin\": \"\", \"@type\": \"definitive\"}]",
    "horaires": "{\"@automate-24-24\": \"\", \"jour\": [{\"@id\": \"1\", \"@nom\": \"Lundi\", \"@ferme\": \"\", \"horaire\": {\"@ouverture\": \"06.30\", \"@fermeture\": \"20.30\"}}, {\"@id\": \"2\", \"@nom\": \"Mardi\", \"@ferme\": \"\", \"horaire\": {\"@ouverture\": \"06.30\", \"@fermeture\": \"20.30\"}}, {\"@id\": \"3\", \"@nom\": \"Mercredi\", \"@ferme\": \"\", \"horaire\": {\"@ouverture\": \"06.30\", \"@fermeture\": \"20.30\"}}, {\"@id\": \"4\", \"@nom\": \"Jeudi\", \"@ferme\": \"\", \"horaire\": {\"@ouverture\": \"06.30\", \"@fermeture\": \"20.30\"}}, {\"@id\": \"5\", \"@nom\": \"Vendredi\", \"@ferme\": \"\", \"horaire\": {\"@ouverture\": \"06.30\", \"@fermeture\": \"21.00\"}}, {\"@id\": \"6\", \"@nom\": \"Samedi\", \"@ferme\": \"\", \"horaire\": {\"@ouverture\": \"07.00\", \"@fermeture\": \"21.00\"}}, {\"@id\": \"7\", \"@nom\": \"Dimanche\", \"@ferme\": \"\", \"horaire\": {\"@ouverture\": \"07.00\", \"@fermeture\": \"20.30\"}}]}",
    "geom": {
      "lon": 4.986,
      "lat": 43.495
    },
    "gazole_maj": "2025-04-02T13:14:14+02:00",
    "gazole_prix": 1.619,
    "sp95_maj": "2025-04-02T13:14:14+02:00",
    "sp95_prix": 1.723,
    "e85_maj": null,
    "e85_prix": null,
    "gplc_maj": null,
    "gplc_prix": null,
    "e10_maj": "2025-04-02T13:14:15+02:00",
    "e10_prix": 1.699,
    "sp98_maj": "2025-04-02T13:14:15+02:00",
    "sp98_prix": 1.799,
    "e10_rupture_debut": null,
    "e10_rupture_type": null,
    "sp98_rupture_debut": null,
    "sp98_rupture_type": null,
    "sp95_rupture_debut": null,
    "sp95_rupture_type": null,
    "e85_rupture_debut": "2017-09-06T22:27:15+02:00",
    "e85_rupture_type": "definitive",
    "gplc_rupture_debut": "2017-09-06T22:27:15+02:00",
    "gplc_rupture_type": "definitive",
    "gazole_rupture_debut": null,
    "gazole_rupture_type": null,
    "carburants_disponibles": [
      "Gazole",
      "SP95",
      "E10",
      "SP98"
    ],
    "carburants_indisponibles": [
      "E85",
      "GPLc"
    ],
    "carburants_rupture_temporaire": null,
    "carburants_rupture_definitive": "E85;GPLc",
    "horaires_automate_24_24": "Non",
    "services_service": [
      "Toilettes publiques",
      "Boutique alimentaire",
      "Boutique non alimentaire",
      "Restauration à emporter",
      "Station de gonflage",
      "Carburant additivé",
      "Location de véhicule",
      "Lavage automatique",
      "Lavage manuel",
      "Vente de gaz domestique (Butane, Propane)",
      "Vente d'additifs carburants",
      "Wifi"
    ],
    "departement": "Bouches-du-Rhône",
    "code_departement": "13",
    "region": "Provence-Alpes-Côte d'Azur",
    "code_region": "93",
    "horaires_jour": "Lundi06.30-20.30, Mardi06.30-20.30, Mercredi06.30-20.30, Jeudi06.30-20.30, Vendredi06.30-21.00, Samedi07.00-21.00, Dimanche07.00-20.30"
  }
]