[
  {
    "id": 43340001,
    "latitude": "4484947.156",
    "longitude": 385165.664,
    "cp": "43340",
    "pop": "R",
    "adresse": "La Sauvetat",
    "ville": "Landos",
    "services": "{\"service\": [\"Toilettes publiques\", \"Vente de fioul domestique\", \"Station de gonflage\", \"Carburant additivé\", \"Piste poids lourds\", \"Espace bébé\", \"DAB (Distributeur automatique de billets)\"]}",
    "prix": "[{\"@nom\": \"Gazole\", \"@id\": \"1\", \"@maj\": \"2024-02-15 05:58:25\", \"@valeur\": \"1.819\"}, {\"@nom\": \"SP95\", \"@id\": \"2\", \"@maj\": \"2024-02-15 05:58:26\", \"@valeur\": \"1.899\"}, {\"@nom\": \"E85\", \"@id\": \"3\", \"@maj\": \"2024-02-15 05:58:26\", \"@valeur\": \"0.909\"}]",
    "horaires": null,
    "geom": {
      "lon": 3.85165664,
      "lat": 44.849471560000005
    },
    "gazole_maj": "2024-02-15T06:58:25+01:00",
    "gazole_prix": "1.819",
    "sp95_maj": "2024-02-15T06:58:26+01:00",
    "sp95_prix": "1.899",
    "e85_maj": "2024-02-15T06:58:26+01:00",
    "e85_prix": "0.909",
    "gplc_maj": null,
    "gplc_prix": null,
    "e10_maj": null,
    "e10_prix": null,
    "sp98_maj": null,
    "sp98_prix": null,
    "carburants_disponibles": [
      "Gazole",
      "SP95",
      "E85"
    ],
    "carburants_indisponibles": [
      "GPLc",
      "E10",
      "SP98"
    ],
    "horaires_automate_24_24": "Non",
    "services_service": [
      "Toilettes publiques",
      "Vente de fioul domestique",
      "Station de gonflage",
      "Carburant additivé",
      "Piste poids lourds",
      "Espace bébé",
      "DAB (Distributeur automatique de billets)"
    ],
    "departement": "Haute-Loire",
    "code_departement": "43",
    "region": "Auvergne-Rhône-Alpes",
    "code_region": "84"
  }
]