[
  {
    "id": 34490002,
    "latitude": "4337665.86291",
    "longitude": 317792.619218,
    "cp": "34490",
    "pop": "R",
    "adresse": "Z.a.e. de Montaury",
    "ville": "Lignan-sur-Orb",
    "services": "{\"service\": [\"Station de gonflage\", \"Vente de gaz domestique (Butane, Propane)\", \"DAB (Distributeur automatique de billets)\"]}",
    "prix": "[{\"@nom\": \"Gazole\", \"@id\": \"1\", \"@maj\": \"2024-01-29 09:08:26\", \"@valeur\": \"1.749\"}, {\"@nom\": \"E85\", \"@id\": \"3\", \"@maj\": \"2024-01-19 09:28:22\", \"@valeur\": \"0.848\"}, {\"@nom\": \"E10\", \"@id\": \"5\", \"@maj\": \"2024-01-29 09:08:26\", \"@valeur\": \"1.784\"}, {\"@nom\": \"SP98\", \"@id\": \"6\", \"@maj\": \"2024-01-29 09:08:27\", \"@valeur\": \"1.862\"}]",
    "horaires": null,
    "geom": {
      "lon": 3.1779261921799997,
      "lat": 43.3766586291
    },
    "gazole_maj": "2024-01-29T10:08:26+01:00",
    "gazole_prix": "1.749",
    "sp95_maj": null,
    "sp95_prix": null,
    "e85_maj": "2024-01-19T10:28:22+01:00",
    "e85_prix": "0.848",
    "gplc_maj": null,
    "gplc_prix": null,
    "e10_maj": "2024-01-29T10:08:26+01:00",
    "e10_prix": "1.784",
    "sp98_maj": "2024-01-29T10:08:27+01:00",
    "sp98_prix": "1.862",
    "carburants_disponibles": [
      "Gazole",
      "E85",
      "E10",
      "SP98"
    ],
    "carburants_indisponibles": [
      "SP95",
      "GPLc"
    ],
    "horaires_automate_24_24": "Non",
    "services_service": [
      "Station de gonflage",
      "Vente de gaz domestique (Butane, Propane)",
      "DAB (Distributeur automatique de billets)"
    ],
    "departement": "Hérault",
    "code_departement": "34",
    "region": "Occitanie",
    "code_region": "76"
  }
]