[
  {
    "id": 34370002,
    "latitude": "4335964.8853961",
    "longitude": 316945.27990723,
    "cp": "34370",
    "pop": "R",
    "adresse": "CHEMIN DE PAYSSIEROU, CENTRE COMMERCIAL LE LIROU",
    "ville": "Maraussan",
    "horaires": "{\"@automate-24-24\": \"\", \"jour\": [{\"@id\": \"1\", \"@nom\": \"Lundi\", \"@ferme\": \"\", \"horaire\": {\"@ouverture\": \"00.00\", \"@fermeture\": \"23.59\"}}, {\"@id\": \"2\", \"@nom\": \"Mardi\", \"@ferme\": \"\", \"horaire\": {\"@ouverture\": \"00.00\", \"@fermeture\": \"23.59\"}}, {\"@id\": \"3\", \"@nom\": \"Mercredi\", \"@ferme\": \"\", \"horaire\": {\"@ouverture\": \"00.00\", \"@fermeture\": \"23.59\"}}, {\"@id\": \"4\", \"@nom\": \"Jeudi\", \"@ferme\": \"\", \"horaire\": {\"@ouverture\": \"00.00\", \"@fermeture\": \"23.59\"}}, {\"@id\": \"5\", \"@nom\": \"Vendredi\", \"@ferme\": \"\", \"horaire\": {\"@ouverture\": \"00.00\", \"@fermeture\": \"23.59\"}}, {\"@id\": \"6\", \"@nom\": \"Samedi\", \"@ferme\": \"\", \"horaire\": {\"@ouverture\": \"00.00\", \"@fermeture\": \"23.59\"}}, {\"@id\": \"7\", \"@nom\": \"Dimanche\", \"@ferme\": \"\", \"horaire\": {\"@ouverture\": \"00.00\", \"@fermeture\": \"23.59\"}}]}",
    "services": "{\"service\": [\"Location de véhicule\", \"Piste poids lourds\", \"Vente de gaz domestique (Butane, Propane)\", \"Wifi\"]}",
    "prix": "[{\"@nom\": \"Gazole\", \"@id\": \"1\", \"@maj\": \"2023-12-29 17:34:50\", \"@valeur\": \"1.729\"}, {\"@nom\": \"E85\", \"@id\": \"3\", \"@maj\": \"2023-12-02 20:00:00\", \"@valeur\": \"0.999\"}, {\"@nom\": \"E10\", \"@id\": \"5\", \"@maj\": \"2023-12-29 17:34:51\", \"@valeur\": \"1.779\"}, {\"@nom\": \"SP98\", \"@id\": \"6\", \"@maj\": \"2023-12-22 12:44:12\", \"@valeur\": \"1.889\"}]",
    "geom": {
      "lon": 3.1694527990723,
      "lat": 43.359648853961
    },
    "gazole_maj": "2023-12-29T18:34:50+01:00",
    "gazole_prix": "1.729",
    "sp95_maj": null,
    "sp95_prix": null,
    "e85_maj": "2023-12-02T21:00:00+01:00",
    "e85_prix": "0.999",
    "gplc_maj": null,
    "gplc_prix": null,
    "e10_maj": "2023-12-29T18:34:51+01:00",
    "e10_prix": "1.779",
    "sp98_maj": "2023-12-22T13:44:12+01:00",
    "sp98_prix": "1.889",
    "carburants_disponibles": [
      "Gazole",
      "E85",
      "E10",
      "SP98"
    ],
    "carburants_indisponibles": [
      "SP95",
      "GPLc"
    ],
    "horaires_automate_24_24": "Non",
    "services_service": [
      "Location de véhicule",
      "Piste poids lourds",
      "Vente de gaz domestique (Butane, Propane)",
      "Wifi"
    ],
    "departement": "Hérault",
    "code_departement": "34",
    "region": "Occitanie",
    "code_region": "76"
  }
]