[
  {
    "id": 47800004,
    "latitude": "4460000",
    "longitude": "35900",
    "cp": "47800",
    "pop": "R",
    "adresse": "12 place Martignac",
    "ville": "Miramont-de-Guyenne",
    "services": "{\"service\": [\"Boutique non alimentaire\", \"Vente de fioul domestique\", \"Carburant additivé\", \"Piste poids lourds\", \"Vente de gaz domestique (Butane, Propane)\", \"Automate CB 24/24\"]}",
    "prix": "[{\"@nom\": \"Gazole\", \"@id\": \"1\", \"@maj\": \"2025-01-23 08:08:03\", \"@valeur\": \"1.869\"}, {\"@nom\": \"SP95\", \"@id\": \"2\", \"@maj\": \"2025-01-23 08:08:03\", \"@valeur\": \"1.929\"}]",
    "rupture": "[{\"@nom\": \"E85\", \"@id\": \"3\", \"@debut\": \"2018-01-03 12:04:15\", \"@fin\": \"\", \"@type\": \"definitive\"}, {\"@nom\": \"GPLc\", \"@id\": \"4\", \"@debut\": \"2018-01-03 12:04:15\", \"@fin\": \"\", \"@type\": \"definitive\"}, {\"@nom\": \"E10\", \"@id\": \"5\", \"@debut\": \"2018-01-03 12:04:15\", \"@fin\": \"\", \"@type\": \"definitive\"}, {\"@nom\": \"SP98\", \"@id\": \"6\", \"@debut\": \"2022-11-27 12:34:44\", \"@fin\": \"\", \"@type\": \"definitive\"}]",
    "horaires": "{\"@automate-24-24\": \"1\", \"jour\": [{\"@id\": \"1\", \"@nom\": \"Lundi\", \"@ferme\": \"\", \"horaire\": {\"@ouverture\": \"00.00\", \"@fermeture\": \"23.59\"}}, {\"@id\": \"2\", \"@nom\": \"Mardi\", \"@ferme\": \"\", \"horaire\": {\"@ouverture\": \"00.00\", \"@fermeture\": \"23.59\"}}, {\"@id\": \"3\", \"@nom\": \"Mercredi\", \"@ferme\": \"\", \"horaire\": {\"@ouverture\": \"00.00\", \"@fermeture\": \"23.59\"}}, {\"@id\": \"4\", \"@nom\": \"Jeudi\", \"@ferme\": \"\", \"horaire\": {\"@ouverture\": \"00.00\", \"@fermeture\": \"23.59\"}}, {\"@id\": \"5\", \"@nom\": \"Vendredi\", \"@ferme\": \"\", \"horaire\": {\"@ouverture\": \"00.00\", \"@fermeture\": \"23.59\"}}, {\"@id\": \"6\", \"@nom\": \"Samedi\", \"@ferme\": \"\", \"horaire\": {\"@ouverture\": \"00.00\", \"@fermeture\": \"23.59\"}}, {\"@id\": \"7\", \"@nom\": \"Dimanche\", \"@ferme\": \"\", \"horaire\": {\"@ouverture\": \"00.00\", \"@fermeture\": \"23.59\"}}]}",
    "geom": {
      "lon": 0.359,
      "lat": 44.6
    },
    "gazole_maj": "2025-01-23T09:08:03+01:00",
    "gazole_prix": 1.869,
    "sp95_maj": "2025-01-23T09:08:03+01:00",
    "sp95_prix": 1.929,
    "e85_maj": null,
    "e85_prix": null,
    "gplc_maj": null,
    "gplc_prix": null,
    "e10_maj": null,
    "e10_prix": null,
    "sp98_maj": null,
    "sp98_prix": null,
    "e10_rupture_debut": "2018-01-03T13:04:15+01:00",
    "e10_rupture_type": "definitive",
    "sp98_rupture_debut": "2022-11-27T13:34:44+01:00",
    "sp98_rupture_type": "definitive",
    "sp95_rupture_debut": null,
    "sp95_rupture_type": null,
    "e85_rupture_debut": "2018-01-03T13:04:15+01:00",
    "e85_rupture_type": "definitive",
    "gplc_rupture_debut": "2018-01-03T13:04:15+01:00",
    "gplc_rupture_type": "definitive",
    "gazole_rupture_debut": null,
    "gazole_rupture_type": null,
    "carburants_disponibles": [
      "Gazole",
      "SP95"
    ],
    "carburants_indisponibles": [
      "E85",
      "GPLc",
      "E10",
      "SP98"
    ],
    "carburants_rupture_temporaire": null,
    "carburants_rupture_definitive": "E85;GPLc;E10;SP98",
    "horaires_automate_24_24": "Oui",
    "services_service": [
      "Boutique non alimentaire",
      "Vente de fioul domestique",
      "Carburant additivé",
      "Piste poids lourds",
      "Vente de gaz domestique (Butane, Propane)",
      "Automate CB 24/24"
    ],
    "departement": "Lot-et-Garonne",
    "code_departement": "47",
    "region": "Nouvelle-Aquitaine",
    "code_region": "75",
    "horaires_jour": "Automate-24-24, Lundi00.00-23.59, Mardi00.00-23.59, Mercredi00.00-23.59, Jeudi00.00-23.59, Vendredi00.00-23.59, Samedi00.00-23.59, Dimanche00.00-23.59"
  },
  {
    "id": 47800003,
    "latitude": "4459548",
    "longitude": "35238",
    "cp": "47800",
    "pop": "R",
    "adresse": "Avenue Alfred Court",
    "ville": "Miramont-de-Guyenne",
    "services": "{\"service\": [\"Vente de gaz domestique (Butane, Propane)\", \"DAB (Distributeur automatique de billets)\"]}",
    "prix": "[{\"@nom\": \"Gazole\", \"@id\": \"1\", \"@maj\": \"2025-01-20 15:37:52\", \"@valeur\": \"1.715\"}, {\"@nom\": \"SP95\", \"@id\": \"2\", \"@maj\": \"2025-01-20 15:37:52\", \"@valeur\": \"1.779\"}, {\"@nom\": \"SP98\", \"@id\": \"6\", \"@maj\": \"2025-01-10 09:00:00\", \"@valeur\": \"1.805\"}]",
    "rupture": "[{\"@nom\": \"E85\", \"@id\": \"3\", \"@debut\": \"2024-07-19 07:40:15\", \"@fin\": \"\", \"@type\": \"definitive\"}, {\"@nom\": \"GPLc\", \"@id\": \"4\", \"@debut\": \"2024-07-19 07:40:15\", \"@fin\": \"\", \"@type\": \"definitive\"}, {\"@nom\": \"E10\", \"@id\": \"5\", \"@debut\": \"2022-04-21 09:46:20\", \"@fin\": \"\", \"@type\": \"definitive\"}]",
    "horaires": null,
    "geom": {
      "lon": 0.35238,
      "lat": 44.59548
    },
    "gazole_maj": "2025-01-20T16:37:52+01:00",
    "gazole_prix": 1.715,
    "sp95_maj": "2025-01-20T16:37:52+01:00",
    "sp95_prix": 1.779,
    "e85_maj": null,
    "e85_prix": null,
    "gplc_maj": null,
    "gplc_prix": null,
    "e10_maj": null,
    "e10_prix": null,
    "sp98_maj": "2025-01-10T10:00:00+01:00",
    "sp98_prix": 1.805,
    "e10_rupture_debut": "2022-04-21T11:46:20+02:00",
    "e10_rupture_type": "definitive",
    "sp98_rupture_debut": null,
    "sp98_rupture_type": null,
    "sp95_rupture_debut": null,
    "sp95_rupture_type": null,
    "e85_rupture_debut": "2024-07-19T09:40:15+02:00",
    "e85_rupture_type": "definitive",
    "gplc_rupture_debut": "2024-07-19T09:40:15+02:00",
    "gplc_rupture_type": "definitive",
    "gazole_rupture_debut": null,
    "gazole_rupture_type": null,
    "carburants_disponibles": [
      "Gazole",
      "SP95",
      "SP98"
    ],
    "carburants_indisponibles": [
      "E85",
      "GPLc",
      "E10"
    ],
    "carburants_rupture_temporaire": null,
    "carburants_rupture_definitive": "E85;GPLc;E10",
    "horaires_automate_24_24": "Non",
    "services_service": [
      "Vente de gaz domestique (Butane, Propane)",
      "DAB (Distributeur automatique de billets)"
    ],
    "departement": "Lot-et-Garonne",
    "code_departement": "47",
    "region": "Nouvelle-Aquitaine",
    "code_region": "75",
    "horaires_jour": null
  }
]