[
  {
    "id": 43290002,
    "latitude": "4518135.9373512",
    "longitude": "431411.24833937",
    "cp": "43290",
    "pop": "R",
    "adresse": "30 AVENUE DES CEVENNES",
    "ville": "Montfaucon-en-Velay",
    "services": "{\"service\": [\"Boutique non alimentaire\", \"Station de gonflage\", \"Lavage manuel\", \"Services réparation / entretien\", \"Vente de gaz domestique (Butane, Propane)\", \"Automate CB 24/24\"]}",
    "prix": "[{\"@nom\": \"Gazole\", \"@id\": \"1\", \"@maj\": \"2026-04-23 15:14:56\", \"@valeur\": \"2.249\"}, {\"@nom\": \"SP95\", \"@id\": \"2\", \"@maj\": \"2026-04-23 15:14:56\", \"@valeur\": \"1.989\"}]",
    "rupture": "[{\"@nom\": \"GPLc\", \"@id\": \"4\", \"@debut\": \"2026-04-23 15:14:56\", \"@fin\": \"\", \"@type\": \"definitive\"}, {\"@nom\": \"E85\", \"@id\": \"3\", \"@debut\": \"2026-04-23 15:14:56\", \"@fin\": \"\", \"@type\": \"definitive\"}, {\"@nom\": \"E10\", \"@id\": \"5\", \"@debut\": \"2026-04-23 15:14:56\", \"@fin\": \"\", \"@type\": \"definitive\"}, {\"@nom\": \"SP98\", \"@id\": \"6\", \"@debut\": \"2026-04-23 15:14:56\", \"@fin\": \"\", \"@type\": \"definitive\"}]",
    "horaires": "{\"@automate-24-24\": \"1\", \"jour\": [{\"@id\": \"1\", \"@nom\": \"Lundi\", \"@ferme\": \"1\"}, {\"@id\": \"2\", \"@nom\": \"Mardi\", \"@ferme\": \"\"}, {\"@id\": \"3\", \"@nom\": \"Mercredi\", \"@ferme\": \"\"}, {\"@id\": \"4\", \"@nom\": \"Jeudi\", \"@ferme\": \"\"}, {\"@id\": \"5\", \"@nom\": \"Vendredi\", \"@ferme\": \"\"}, {\"@id\": \"6\", \"@nom\": \"Samedi\", \"@ferme\": \"\"}, {\"@id\": \"7\", \"@nom\": \"Dimanche\", \"@ferme\": \"1\"}]}",
    "geom": {
      "lon": 4.3141124833937,
      "lat": 45.181359373511995
    },
    "gazole_maj": "2026-04-23T17:14:56+02:00",
    "gazole_prix": 2.249,
    "sp95_maj": "2026-04-23T17:14:56+02:00",
    "sp95_prix": 1.989,
    "e85_maj": null,
    "e85_prix": null,
    "gplc_maj": null,
    "gplc_prix": null,
    "e10_maj": null,
    "e10_prix": null,
    "sp98_maj": null,
    "sp98_prix": null,
    "e10_rupture_debut": "2026-04-23T17:14:56+02:00",
    "e10_rupture_type": "definitive",
    "sp98_rupture_debut": "2026-04-23T17:14:56+02:00",
    "sp98_rupture_type": "definitive",
    "sp95_rupture_debut": null,
    "sp95_rupture_type": null,
    "e85_rupture_debut": "2026-04-23T17:14:56+02:00",
    "e85_rupture_type": "definitive",
    "gplc_rupture_debut": "2026-04-23T17:14:56+02:00",
    "gplc_rupture_type": "definitive",
    "gazole_rupture_debut": null,
    "gazole_rupture_type": null,
    "carburants_disponibles": [
      "Gazole",
      "SP95"
    ],
    "carburants_indisponibles": [
      "E85",
      "GPLc",
      "E10",
      "SP98"
    ],
    "carburants_rupture_temporaire": null,
    "carburants_rupture_definitive": "E85;GPLc;E10;SP98",
    "horaires_automate_24_24": "Oui",
    "services_service": [
      "Boutique non alimentaire",
      "Station de gonflage",
      "Lavage manuel",
      "Services réparation / entretien",
      "Vente de gaz domestique (Butane, Propane)",
      "Automate CB 24/24"
    ],
    "departement": "Haute-Loire",
    "code_departement": "43",
    "region": "Auvergne-Rhône-Alpes",
    "code_region": "84",
    "horaires_jour": "Automate-24-24"
  },
  {
    "id": 43290001,
    "latitude": "4518157",
    "longitude": "431425",
    "cp": "43290",
    "pop": "R",
    "adresse": "9 av Cévennes",
    "ville": "Montfaucon-en-Velay",
    "services": "{\"service\": [\"Boutique non alimentaire\", \"Vente de fioul domestique\", \"Station de gonflage\"]}",
    "prix": "[{\"@nom\": \"Gazole\", \"@id\": \"1\", \"@maj\": \"2026-06-03 07:57:48\", \"@valeur\": \"2.010\"}, {\"@nom\": \"SP95\", \"@id\": \"2\", \"@maj\": \"2026-06-03 07:57:49\", \"@valeur\": \"2.090\"}]",
    "rupture": "[{\"@nom\": \"E85\", \"@id\": \"3\", \"@debut\": \"2019-01-29 11:01:29\", \"@fin\": \"\", \"@type\": \"definitive\"}, {\"@nom\": \"GPLc\", \"@id\": \"4\", \"@debut\": \"2019-01-29 11:01:29\", \"@fin\": \"\", \"@type\": \"definitive\"}, {\"@nom\": \"E10\", \"@id\": \"5\", \"@debut\": \"2019-01-29 11:01:29\", \"@fin\": \"\", \"@type\": \"definitive\"}, {\"@nom\": \"SP98\", \"@id\": \"6\", \"@debut\": \"2019-01-29 11:01:29\", \"@fin\": \"\", \"@type\": \"definitive\"}]",
    "horaires": null,
    "geom": {
      "lon": 4.31425,
      "lat": 45.18157
    },
    "gazole_maj": "2026-06-03T09:57:48+02:00",
    "gazole_prix": 2.01,
    "sp95_maj": "2026-06-03T09:57:49+02:00",
    "sp95_prix": 2.09,
    "e85_maj": null,
    "e85_prix": null,
    "gplc_maj": null,
    "gplc_prix": null,
    "e10_maj": null,
    "e10_prix": null,
    "sp98_maj": null,
    "sp98_prix": null,
    "e10_rupture_debut": "2019-01-29T12:01:29+01:00",
    "e10_rupture_type": "definitive",
    "sp98_rupture_debut": "2019-01-29T12:01:29+01:00",
    "sp98_rupture_type": "definitive",
    "sp95_rupture_debut": null,
    "sp95_rupture_type": null,
    "e85_rupture_debut": "2019-01-29T12:01:29+01:00",
    "e85_rupture_type": "definitive",
    "gplc_rupture_debut": "2019-01-29T12:01:29+01:00",
    "gplc_rupture_type": "definitive",
    "gazole_rupture_debut": null,
    "gazole_rupture_type": null,
    "carburants_disponibles": [
      "Gazole",
      "SP95"
    ],
    "carburants_indisponibles": [
      "E85",
      "GPLc",
      "E10",
      "SP98"
    ],
    "carburants_rupture_temporaire": null,
    "carburants_rupture_definitive": "E85;GPLc;E10;SP98",
    "horaires_automate_24_24": "Non",
    "services_service": [
      "Boutique non alimentaire",
      "Vente de fioul domestique",
      "Station de gonflage"
    ],
    "departement": "Haute-Loire",
    "code_departement": "43",
    "region": "Auvergne-Rhône-Alpes",
    "code_region": "84",
    "horaires_jour": null
  }
]