[
  {
    "id": 24300004,
    "latitude": "4554059",
    "longitude": "66713",
    "cp": "24300",
    "pop": "R",
    "adresse": "2 Route de la Maladrerie",
    "ville": "Nontron",
    "services": "{\"service\": [\"Boutique alimentaire\", \"Restauration à emporter\", \"Restauration sur place\", \"Bar\", \"Station de gonflage\", \"Location de véhicule\", \"Lavage automatique\", \"Lavage manuel\", \"Vente de gaz domestique (Butane, Propane)\", \"DAB (Distributeur automatique de billets)\"]}",
    "prix": "[{\"@nom\": \"Gazole\", \"@id\": \"1\", \"@maj\": \"2026-02-07 13:46:29\", \"@valeur\": \"1.653\"}, {\"@nom\": \"SP95\", \"@id\": \"2\", \"@maj\": \"2026-02-07 13:46:29\", \"@valeur\": \"1.722\"}, {\"@nom\": \"E10\", \"@id\": \"5\", \"@maj\": \"2026-02-07 13:46:29\", \"@valeur\": \"1.664\"}, {\"@nom\": \"SP98\", \"@id\": \"6\", \"@maj\": \"2026-02-07 13:46:29\", \"@valeur\": \"1.731\"}]",
    "rupture": "[{\"@nom\": \"E85\", \"@id\": \"3\", \"@debut\": \"2025-10-31 09:04:18\", \"@fin\": \"\", \"@type\": \"definitive\"}, {\"@nom\": \"GPLc\", \"@id\": \"4\", \"@debut\": \"2025-10-31 09:04:18\", \"@fin\": \"\", \"@type\": \"definitive\"}]",
    "horaires": null,
    "geom": {
      "lon": 0.66713,
      "lat": 45.54059
    },
    "gazole_maj": "2026-02-07T14:46:29+01:00",
    "gazole_prix": 1.653,
    "sp95_maj": "2026-02-07T14:46:29+01:00",
    "sp95_prix": 1.722,
    "e85_maj": null,
    "e85_prix": null,
    "gplc_maj": null,
    "gplc_prix": null,
    "e10_maj": "2026-02-07T14:46:29+01:00",
    "e10_prix": 1.664,
    "sp98_maj": "2026-02-07T14:46:29+01:00",
    "sp98_prix": 1.731,
    "e10_rupture_debut": null,
    "e10_rupture_type": null,
    "sp98_rupture_debut": null,
    "sp98_rupture_type": null,
    "sp95_rupture_debut": null,
    "sp95_rupture_type": null,
    "e85_rupture_debut": "2025-10-31T10:04:18+01:00",
    "e85_rupture_type": "definitive",
    "gplc_rupture_debut": "2025-10-31T10:04:18+01:00",
    "gplc_rupture_type": "definitive",
    "gazole_rupture_debut": null,
    "gazole_rupture_type": null,
    "carburants_disponibles": [
      "Gazole",
      "SP95",
      "E10",
      "SP98"
    ],
    "carburants_indisponibles": [
      "E85",
      "GPLc"
    ],
    "carburants_rupture_temporaire": null,
    "carburants_rupture_definitive": "E85;GPLc",
    "horaires_automate_24_24": "Non",
    "services_service": [
      "Boutique alimentaire",
      "Restauration à emporter",
      "Restauration sur place",
      "Bar",
      "Station de gonflage",
      "Location de véhicule",
      "Lavage automatique",
      "Lavage manuel",
      "Vente de gaz domestique (Butane, Propane)",
      "DAB (Distributeur automatique de billets)"
    ],
    "departement": "Dordogne",
    "code_departement": "24",
    "region": "Nouvelle-Aquitaine",
    "code_region": "75",
    "horaires_jour": null
  },
  {
    "id": 24300001,
    "latitude": "4553400",
    "longitude": "66600",
    "cp": "24300",
    "pop": "R",
    "adresse": "28, avenue Jules-Ferry",
    "ville": "Nontron",
    "services": "{\"service\": [\"Laverie\", \"Restauration à emporter\", \"Restauration sur place\", \"Location de véhicule\", \"Vente de gaz domestique (Butane, Propane)\", \"Wifi\", \"Automate CB 24/24\"]}",
    "prix": "[{\"@nom\": \"Gazole\", \"@id\": \"1\", \"@maj\": \"2026-01-29 09:04:31\", \"@valeur\": \"1.676\"}, {\"@nom\": \"E85\", \"@id\": \"3\", \"@maj\": \"2025-10-18 04:56:19\", \"@valeur\": \"0.757\"}, {\"@nom\": \"E10\", \"@id\": \"5\", \"@maj\": \"2026-01-29 09:09:11\", \"@valeur\": \"1.672\"}, {\"@nom\": \"SP98\", \"@id\": \"6\", \"@maj\": \"2026-01-29 09:04:31\", \"@valeur\": \"1.760\"}]",
    "rupture": "[{\"@nom\": \"SP95\", \"@id\": \"2\", \"@debut\": \"2024-07-19 10:15:27\", \"@fin\": \"\", \"@type\": \"definitive\"}, {\"@nom\": \"GPLc\", \"@id\": \"4\", \"@debut\": \"2024-07-19 10:15:27\", \"@fin\": \"\", \"@type\": \"definitive\"}]",
    "horaires": "{\"@automate-24-24\": \"1\", \"jour\": [{\"@id\": \"1\", \"@nom\": \"Lundi\", \"@ferme\": \"\"}, {\"@id\": \"2\", \"@nom\": \"Mardi\", \"@ferme\": \"\"}, {\"@id\": \"3\", \"@nom\": \"Mercredi\", \"@ferme\": \"\"}, {\"@id\": \"4\", \"@nom\": \"Jeudi\", \"@ferme\": \"\"}, {\"@id\": \"5\", \"@nom\": \"Vendredi\", \"@ferme\": \"\"}, {\"@id\": \"6\", \"@nom\": \"Samedi\", \"@ferme\": \"\"}, {\"@id\": \"7\", \"@nom\": \"Dimanche\", \"@ferme\": \"\"}]}",
    "geom": {
      "lon": 0.666,
      "lat": 45.534
    },
    "gazole_maj": "2026-01-29T10:04:31+01:00",
    "gazole_prix": 1.676,
    "sp95_maj": null,
    "sp95_prix": null,
    "e85_maj": "2025-10-18T06:56:19+02:00",
    "e85_prix": 0.757,
    "gplc_maj": null,
    "gplc_prix": null,
    "e10_maj": "2026-01-29T10:09:11+01:00",
    "e10_prix": 1.672,
    "sp98_maj": "2026-01-29T10:04:31+01:00",
    "sp98_prix": 1.76,
    "e10_rupture_debut": null,
    "e10_rupture_type": null,
    "sp98_rupture_debut": null,
    "sp98_rupture_type": null,
    "sp95_rupture_debut": "2024-07-19T12:15:27+02:00",
    "sp95_rupture_type": "definitive",
    "e85_rupture_debut": null,
    "e85_rupture_type": null,
    "gplc_rupture_debut": "2024-07-19T12:15:27+02:00",
    "gplc_rupture_type": "definitive",
    "gazole_rupture_debut": null,
    "gazole_rupture_type": null,
    "carburants_disponibles": [
      "Gazole",
      "E85",
      "E10",
      "SP98"
    ],
    "carburants_indisponibles": [
      "SP95",
      "GPLc"
    ],
    "carburants_rupture_temporaire": null,
    "carburants_rupture_definitive": "SP95;GPLc",
    "horaires_automate_24_24": "Oui",
    "services_service": [
      "Laverie",
      "Restauration à emporter",
      "Restauration sur place",
      "Location de véhicule",
      "Vente de gaz domestique (Butane, Propane)",
      "Wifi",
      "Automate CB 24/24"
    ],
    "departement": "Dordogne",
    "code_departement": "24",
    "region": "Nouvelle-Aquitaine",
    "code_region": "75",
    "horaires_jour": "Automate-24-24"
  }
]