[
  {
    "id": 22110002,
    "latitude": "4824221.6194891",
    "longitude": -329616.6474018,
    "cp": "22110",
    "pop": "R",
    "adresse": "KERLOUIS",
    "ville": "Plouguernével",
    "horaires": null,
    "services": "{\"service\": [\"Toilettes publiques\", \"Relais colis\", \"Boutique alimentaire\", \"Boutique non alimentaire\", \"Vente de gaz domestique (Butane, Propane)\", \"DAB (Distributeur automatique de billets)\"]}",
    "prix": "[{\"@nom\": \"Gazole\", \"@id\": \"1\", \"@maj\": \"2024-01-03 10:15:10\", \"@valeur\": \"1.649\"}, {\"@nom\": \"E10\", \"@id\": \"5\", \"@maj\": \"2024-01-03 10:15:10\", \"@valeur\": \"1.679\"}, {\"@nom\": \"SP98\", \"@id\": \"6\", \"@maj\": \"2024-01-03 10:15:10\", \"@valeur\": \"1.769\"}]",
    "geom": {
      "lon": -3.296166474018,
      "lat": 48.242216194891
    },
    "gazole_maj": "2024-01-03T11:15:10+01:00",
    "gazole_prix": "1.649",
    "sp95_maj": null,
    "sp95_prix": null,
    "e85_maj": null,
    "e85_prix": null,
    "gplc_maj": null,
    "gplc_prix": null,
    "e10_maj": "2024-01-03T11:15:10+01:00",
    "e10_prix": "1.679",
    "sp98_maj": "2024-01-03T11:15:10+01:00",
    "sp98_prix": "1.769",
    "carburants_disponibles": [
      "Gazole",
      "E10",
      "SP98"
    ],
    "carburants_indisponibles": [
      "SP95",
      "E85",
      "GPLc"
    ],
    "horaires_automate_24_24": "Non",
    "services_service": [
      "Toilettes publiques",
      "Relais colis",
      "Boutique alimentaire",
      "Boutique non alimentaire",
      "Vente de gaz domestique (Butane, Propane)",
      "DAB (Distributeur automatique de billets)"
    ],
    "departement": "Côtes-d'Armor",
    "code_departement": "22",
    "region": "Bretagne",
    "code_region": "53"
  }
]