[
  {
    "id": 22110003,
    "latitude": "4823682",
    "longitude": -331209,
    "cp": "22110",
    "pop": "R",
    "adresse": "LE CAP VERT",
    "ville": "Rostrenen",
    "horaires": null,
    "services": null,
    "prix": "[{\"@nom\": \"Gazole\", \"@id\": \"1\", \"@maj\": \"2024-01-31 10:10:23\", \"@valeur\": \"1.749\"}, {\"@nom\": \"GPLc\", \"@id\": \"4\", \"@maj\": \"2023-12-26 10:03:35\", \"@valeur\": \"0.959\"}, {\"@nom\": \"E10\", \"@id\": \"5\", \"@maj\": \"2024-01-31 10:10:23\", \"@valeur\": \"1.765\"}, {\"@nom\": \"SP98\", \"@id\": \"6\", \"@maj\": \"2024-01-31 10:10:24\", \"@valeur\": \"1.829\"}]",
    "geom": {
      "lon": -3.31209,
      "lat": 48.23682
    },
    "gazole_maj": "2024-01-31T11:10:23+01:00",
    "gazole_prix": "1.749",
    "sp95_maj": null,
    "sp95_prix": null,
    "e85_maj": null,
    "e85_prix": null,
    "gplc_maj": "2023-12-26T11:03:35+01:00",
    "gplc_prix": "0.959",
    "e10_maj": "2024-01-31T11:10:23+01:00",
    "e10_prix": "1.765",
    "sp98_maj": "2024-01-31T11:10:24+01:00",
    "sp98_prix": "1.829",
    "carburants_disponibles": [
      "Gazole",
      "GPLc",
      "E10",
      "SP98"
    ],
    "carburants_indisponibles": [
      "SP95",
      "E85"
    ],
    "horaires_automate_24_24": "Non",
    "services_service": null,
    "departement": "Côtes-d'Armor",
    "code_departement": "22",
    "region": "Bretagne",
    "code_region": "53"
  }
]