[
  {
    "id": 17220003,
    "latitude": "4615054.29",
    "longitude": "-107654.119",
    "cp": "17220",
    "pop": "R",
    "adresse": "1Bis Route de la Jarne",
    "ville": "Saint-Rogatien",
    "services": "{\"service\": [\"Toilettes publiques\", \"Relais colis\", \"Station de gonflage\", \"Piste poids lourds\", \"Vente de gaz domestique (Butane, Propane)\", \"DAB (Distributeur automatique de billets)\"]}",
    "prix": "[{\"@nom\": \"Gazole\", \"@id\": \"1\", \"@maj\": \"2025-07-01 08:51:03\", \"@valeur\": \"1.535\"}, {\"@nom\": \"E10\", \"@id\": \"5\", \"@maj\": \"2025-07-01 08:51:03\", \"@valeur\": \"1.595\"}, {\"@nom\": \"SP98\", \"@id\": \"6\", \"@maj\": \"2025-07-01 08:51:03\", \"@valeur\": \"1.682\"}]",
    "rupture": "[{\"@nom\": \"SP95\", \"@id\": \"2\", \"@debut\": \"2018-02-24 09:22:50\", \"@fin\": \"\", \"@type\": \"definitive\"}, {\"@nom\": \"E85\", \"@id\": \"3\", \"@debut\": \"2018-02-24 09:22:50\", \"@fin\": \"\", \"@type\": \"definitive\"}, {\"@nom\": \"GPLc\", \"@id\": \"4\", \"@debut\": \"2018-02-24 09:22:50\", \"@fin\": \"\", \"@type\": \"definitive\"}]",
    "horaires": null,
    "geom": {
      "lon": -1.0765411900000001,
      "lat": 46.1505429
    },
    "gazole_maj": "2025-07-01T10:51:03+02:00",
    "gazole_prix": 1.535,
    "sp95_maj": null,
    "sp95_prix": null,
    "e85_maj": null,
    "e85_prix": null,
    "gplc_maj": null,
    "gplc_prix": null,
    "e10_maj": "2025-07-01T10:51:03+02:00",
    "e10_prix": 1.595,
    "sp98_maj": "2025-07-01T10:51:03+02:00",
    "sp98_prix": 1.682,
    "e10_rupture_debut": null,
    "e10_rupture_type": null,
    "sp98_rupture_debut": null,
    "sp98_rupture_type": null,
    "sp95_rupture_debut": "2018-02-24T10:22:50+01:00",
    "sp95_rupture_type": "definitive",
    "e85_rupture_debut": "2018-02-24T10:22:50+01:00",
    "e85_rupture_type": "definitive",
    "gplc_rupture_debut": "2018-02-24T10:22:50+01:00",
    "gplc_rupture_type": "definitive",
    "gazole_rupture_debut": null,
    "gazole_rupture_type": null,
    "carburants_disponibles": [
      "Gazole",
      "E10",
      "SP98"
    ],
    "carburants_indisponibles": [
      "SP95",
      "E85",
      "GPLc"
    ],
    "carburants_rupture_temporaire": null,
    "carburants_rupture_definitive": "SP95;E85;GPLc",
    "horaires_automate_24_24": "Non",
    "services_service": [
      "Toilettes publiques",
      "Relais colis",
      "Station de gonflage",
      "Piste poids lourds",
      "Vente de gaz domestique (Butane, Propane)",
      "DAB (Distributeur automatique de billets)"
    ],
    "departement": "Charente-Maritime",
    "code_departement": "17",
    "region": "Nouvelle-Aquitaine",
    "code_region": "75",
    "horaires_jour": null
  }
]