[
  {
    "id": 44530003,
    "latitude": "4750937",
    "longitude": "-204035",
    "cp": "44530",
    "pop": "R",
    "adresse": "route de Pontchâteau",
    "ville": "Saint-Gildas-des-Bois",
    "services": null,
    "prix": "[{\"@nom\": \"Gazole\", \"@id\": \"1\", \"@maj\": \"2024-12-04 09:09:00\", \"@valeur\": \"1.589\"}, {\"@nom\": \"SP95\", \"@id\": \"2\", \"@maj\": \"2024-12-04 09:09:01\", \"@valeur\": \"1.689\"}, {\"@nom\": \"SP98\", \"@id\": \"6\", \"@maj\": \"2024-12-04 09:09:01\", \"@valeur\": \"1.729\"}]",
    "rupture": "[{\"@nom\": \"E85\", \"@id\": \"3\", \"@debut\": \"2018-01-06 08:43:48\", \"@fin\": \"\", \"@type\": \"definitive\"}, {\"@nom\": \"E10\", \"@id\": \"5\", \"@debut\": \"2018-01-06 08:43:49\", \"@fin\": \"\", \"@type\": \"definitive\"}]",
    "horaires": null,
    "geom": {
      "lon": -2.04035,
      "lat": 47.50937
    },
    "gazole_maj": "2024-12-04T10:09:00+01:00",
    "gazole_prix": 1.589,
    "sp95_maj": "2024-12-04T10:09:01+01:00",
    "sp95_prix": 1.689,
    "e85_maj": null,
    "e85_prix": null,
    "gplc_maj": null,
    "gplc_prix": null,
    "e10_maj": null,
    "e10_prix": null,
    "sp98_maj": "2024-12-04T10:09:01+01:00",
    "sp98_prix": 1.729,
    "e10_rupture_debut": "2018-01-06T09:43:49+01:00",
    "e10_rupture_type": "definitive",
    "sp98_rupture_debut": null,
    "sp98_rupture_type": null,
    "sp95_rupture_debut": null,
    "sp95_rupture_type": null,
    "e85_rupture_debut": "2018-01-06T09:43:48+01:00",
    "e85_rupture_type": "definitive",
    "gplc_rupture_debut": null,
    "gplc_rupture_type": null,
    "gazole_rupture_debut": null,
    "gazole_rupture_type": null,
    "carburants_disponibles": [
      "Gazole",
      "SP95",
      "SP98"
    ],
    "carburants_indisponibles": [
      "E85",
      "GPLc",
      "E10"
    ],
    "carburants_rupture_temporaire": null,
    "carburants_rupture_definitive": "E85;E10",
    "horaires_automate_24_24": "Non",
    "services_service": null,
    "departement": "Loire-Atlantique",
    "code_departement": "44",
    "region": "Pays de la Loire",
    "code_region": "52",
    "horaires_jour": null
  }
]