[
  {
    "id": 67370002,
    "latitude": "4864346.9159516",
    "longitude": 759854.68752829,
    "cp": "67370",
    "pop": "R",
    "adresse": "5 Allée de l'économie",
    "ville": "Wiwersheim",
    "services": "{\"service\": \"Automate CB 24/24\"}",
    "prix": "[{\"@nom\": \"Gazole\", \"@id\": \"1\", \"@maj\": \"2024-02-27 15:28:05\", \"@valeur\": \"1.819\"}, {\"@nom\": \"E85\", \"@id\": \"3\", \"@maj\": \"2024-02-27 15:28:05\", \"@valeur\": \"0.879\"}, {\"@nom\": \"E10\", \"@id\": \"5\", \"@maj\": \"2024-02-27 15:28:06\", \"@valeur\": \"1.809\"}]",
    "horaires": "{\"@automate-24-24\": \"1\", \"jour\": [{\"@id\": \"1\", \"@nom\": \"Lundi\", \"@ferme\": \"1\", \"horaire\": {\"@ouverture\": \"01.00\", \"@fermeture\": \"01.00\"}}, {\"@id\": \"2\", \"@nom\": \"Mardi\", \"@ferme\": \"1\", \"horaire\": {\"@ouverture\": \"01.00\", \"@fermeture\": \"01.00\"}}, {\"@id\": \"3\", \"@nom\": \"Mercredi\", \"@ferme\": \"1\", \"horaire\": {\"@ouverture\": \"01.00\", \"@fermeture\": \"01.00\"}}, {\"@id\": \"4\", \"@nom\": \"Jeudi\", \"@ferme\": \"1\", \"horaire\": {\"@ouverture\": \"01.00\", \"@fermeture\": \"01.00\"}}, {\"@id\": \"5\", \"@nom\": \"Vendredi\", \"@ferme\": \"1\", \"horaire\": {\"@ouverture\": \"01.00\", \"@fermeture\": \"01.00\"}}, {\"@id\": \"6\", \"@nom\": \"Samedi\", \"@ferme\": \"1\", \"horaire\": {\"@ouverture\": \"01.00\", \"@fermeture\": \"01.00\"}}, {\"@id\": \"7\", \"@nom\": \"Dimanche\", \"@ferme\": \"1\", \"horaire\": {\"@ouverture\": \"01.00\", \"@fermeture\": \"01.00\"}}]}",
    "geom": {
      "lon": 7.598546875282899,
      "lat": 48.643469159516
    },
    "gazole_maj": "2024-02-27T16:28:05+01:00",
    "gazole_prix": "1.819",
    "sp95_maj": null,
    "sp95_prix": null,
    "e85_maj": "2024-02-27T16:28:05+01:00",
    "e85_prix": "0.879",
    "gplc_maj": null,
    "gplc_prix": null,
    "e10_maj": "2024-02-27T16:28:06+01:00",
    "e10_prix": "1.809",
    "sp98_maj": null,
    "sp98_prix": null,
    "carburants_disponibles": [
      "Gazole",
      "E85",
      "E10"
    ],
    "carburants_indisponibles": [
      "SP95",
      "GPLc",
      "SP98"
    ],
    "horaires_automate_24_24": "Oui",
    "services_service": [
      "Automate CB 24/24"
    ],
    "departement": "Bas-Rhin",
    "code_departement": "67",
    "region": "Grand Est",
    "code_region": "44"
  }
]